ai_tools_core/README.md
ai_tools_core/__init__.py
ai_tools_core/logger.py
ai_tools_core/tools.py
ai_tools_core/cli/__init__.py
ai_tools_core/cli/core.py
ai_tools_core/history/__init__.py
ai_tools_core/history/formatters.py
ai_tools_core/history/manager.py
ai_tools_core/history/models.py
ai_tools_core/history/storage.py
ai_tools_core/services/__init__.py
ai_tools_core/services/openai_message_service.py
ai_tools_core/services/openai_service.py
ai_tools_core/services/tool_service.py
ai_tools_core/usage/__init__.py
ai_tools_core/usage/events.py
ai_tools_core/usage/trackers.py
ai_tools_core/utils/__init__.py
ai_tools_core/utils/env.py
bot/__init__.py
bot/billing.py
bot/handlers.py
bot/projects.py
bot/telegram_bot.py
bot/utils.py
utils/__init__.py
utils/env.py
ai_tools_core-0.4.0.dist-info/METADATA
ai_tools_core-0.4.0.dist-info/WHEEL
ai_tools_core-0.4.0.dist-info/entry_points.txt
ai_tools_core-0.4.0.dist-info/top_level.txt
ai_tools_core-0.4.0.dist-info/RECORD
