Metadata-Version: 2.4
Name: ai_tools_core
Version: 0.4.0
Summary: Toolkit for building AI-powered applications with OpenAI and other AI services
Author: idolgoff
Classifier: Development Status :: 3 - Alpha
Classifier: Intended Audience :: Developers
Classifier: Programming Language :: Python :: 3
Classifier: Programming Language :: Python :: 3.8
Classifier: Programming Language :: Python :: 3.9
Classifier: Programming Language :: Python :: 3.10
Classifier: Programming Language :: Python :: 3.11
Classifier: Topic :: Software Development :: Libraries :: Python Modules
Classifier: Topic :: Scientific/Engineering :: Artificial Intelligence
Requires-Python: >=3.8
Requires-Dist: python-dotenv>=1.0.0
Requires-Dist: openai>=1.12.0
Requires-Dist: colorlog>=6.7.0
Requires-Dist: pydantic>=2.5.2
Requires-Dist: tiktoken>=0.5.2
Requires-Dist: watchdog>=3.0.0
Provides-Extra: dev
Requires-Dist: pytest>=7.0.0; extra == "dev"
Requires-Dist: pytest-mock>=3.10.0; extra == "dev"
Provides-Extra: telegram
Requires-Dist: python-telegram-bot>=20.0; extra == "telegram"
Dynamic: requires-python
